{
  "id": "cards_section",
  "type": "SharedSlice",
  "name": "CardsSection",
  "description": "CardsSection",
  "variations": [
    {
      "id": "default",
      "name": "Default",
      "docURL": "...",
      "version": "initial",
      "description": "Default",
      "imageUrl": "",
      "primary": {
        "title": {
          "type": "StructuredText",
          "config": {
            "label": "Title",
            "labels": ["accent-blue", "accent-cyan", "accent-magenta"],
            "placeholder": "",
            "allowTargetBlank": true,
            "multi": "heading1,heading2,heading3,heading4,heading5,heading6,strong,em,paragraph,list-item"
          }
        },
        "textAlignment": {
          "type": "Select",
          "config": {
            "label": "Text Alignment",
            "placeholder": "",
            "options": ["left", "center", "right"]
          }
        },
        "titleColor": {
          "type": "Color",
          "config": {
            "label": "Title Color",
            "placeholder": ""
          }
        },
        "backgroundColor": {
          "type": "Color",
          "config": {
            "label": "Background Color",
            "placeholder": ""
          }
        }
      },
      "items": {
        "title": {
          "type": "Text",
          "config": {
            "label": "Title",
            "placeholder": ""
          }
        },
        "image": {
          "type": "Image",
          "config": {
            "label": "Image",
            "constraint": {},
            "thumbnails": []
          }
        },
        "description": {
          "type": "StructuredText",
          "config": {
            "label": "Description",
            "placeholder": "",
            "allowTargetBlank": true,
            "single": "paragraph,preformatted,heading1,heading2,heading3,heading4,heading5,heading6,strong,em,hyperlink,image,embed,list-item,o-list-item,rtl"
          }
        }
      }
    },
    {
      "id": "payment",
      "name": "Payment",
      "docURL": "...",
      "version": "initial",
      "description": "Default",
      "imageUrl": "",
      "primary": {
        "title": {
          "type": "StructuredText",
          "config": {
            "label": "Title",
            "placeholder": "",
            "allowTargetBlank": true,
            "multi": "heading1,heading2,heading3,heading4,heading5,heading6,strong,em,paragraph,list-item"
          }
        },
        "textAlignment": {
          "type": "Select",
          "config": {
            "label": "Text Alignment",
            "placeholder": "",
            "options": ["left", "center", "right"]
          }
        },
        "titleColor": {
          "type": "Color",
          "config": {
            "label": "Title Color",
            "placeholder": ""
          }
        },
        "backgroundColor": {
          "type": "Color",
          "config": {
            "label": "Background Color",
            "placeholder": ""
          }
        }
      },
      "items": {
        "title": {
          "type": "Text",
          "config": {
            "label": "Title",
            "placeholder": ""
          }
        },
        "image": {
          "type": "Image",
          "config": {
            "label": "Image",
            "constraint": {},
            "thumbnails": []
          }
        },
        "description": {
          "type": "StructuredText",
          "config": {
            "label": "Description",
            "placeholder": "",
            "allowTargetBlank": true,
            "single": "paragraph,preformatted,heading1,heading2,heading3,heading4,heading5,heading6,strong,em,hyperlink,image,embed,list-item,o-list-item,rtl"
          }
        }
      }
    }
  ]
}
